{
    "today": "2023-12-17 00:16:45.616841",
    "title": [
        "92号汽油",
        "95号汽油",
        "98号汽油",
        "0号柴油"
    ],
    "group": [
        {
            "location": "北京",
            "data": [
                "7.88",
                "8.39",
                "9.88",
                "7.59"
            ]
        },
        {
            "location": "上海",
            "data": [
                "7.84",
                "8.34",
                "9.34",
                "7.52"
            ]
        },
        {
            "location": "江苏",
            "data": [
                "7.85",
                "8.35",
                "9.85",
                "7.50"
            ]
        },
        {
            "location": "天津",
            "data": [
                "7.87",
                "8.32",
                "9.75",
                "7.55"
            ]
        },
        {
            "location": "重庆",
            "data": [
                "7.94",
                "8.39",
                "9.45",
                "7.61"
            ]
        },
        {
            "location": "江西",
            "data": [
                "7.84",
                "8.41",
                "9.91",
                "7.59"
            ]
        },
        {
            "location": "辽宁",
            "data": [
                "7.96",
                "8.49",
                "9.24",
                "7.44"
            ]
        },
        {
            "location": "安徽",
            "data": [
                "7.83",
                "8.38",
                "9.40",
                "7.58"
            ]
        },
        {
            "location": "内蒙古",
            "data": [
                "7.81",
                "8.33",
                "9.15",
                "7.41"
            ]
        },
        {
            "location": "福建",
            "data": [
                "7.84",
                "8.37",
                "9.37",
                "7.53"
            ]
        },
        {
            "location": "宁夏",
            "data": [
                "7.78",
                "8.22",
                "9.38",
                "7.42"
            ]
        },
        {
            "location": "甘肃",
            "data": [
                "7.88",
                "8.41",
                "0",
                "7.44"
            ]
        },
        {
            "location": "青海",
            "data": [
                "7.83",
                "8.40",
                "9.15",
                "7.46"
            ]
        },
        {
            "location": "广东",
            "data": [
                "7.90",
                "8.55",
                "10.55",
                "7.55"
            ]
        },
        {
            "location": "山东",
            "data": [
                "7.84",
                "8.41",
                "9.13",
                "7.46"
            ]
        },
        {
            "location": "广西",
            "data": [
                "7.93",
                "8.57",
                "9.70",
                "7.60"
            ]
        },
        {
            "location": "山西",
            "data": [
                "7.82",
                "8.45",
                "9.15",
                "7.61"
            ]
        },
        {
            "location": "贵州",
            "data": [
                "8.01",
                "8.46",
                "9.36",
                "7.65"
            ]
        },
        {
            "location": "陕西",
            "data": [
                "7.76",
                "8.20",
                "10.76",
                "7.43"
            ]
        },
        {
            "location": "海南",
            "data": [
                "8.99",
                "9.55",
                "10.81",
                "7.63"
            ]
        },
        {
            "location": "四川",
            "data": [
                "7.97",
                "8.52",
                "9.26",
                "7.59"
            ]
        },
        {
            "location": "河北",
            "data": [
                "7.87",
                "8.32",
                "9.14",
                "7.55"
            ]
        },
        {
            "location": "西藏",
            "data": [
                "8.75",
                "9.26",
                "10.32",
                "8.08"
            ]
        },
        {
            "location": "河南",
            "data": [
                "7.88",
                "8.42",
                "9.22",
                "7.53"
            ]
        },
        {
            "location": "新疆",
            "data": [
                "7.70",
                "8.24",
                "9.17",
                "7.32"
            ]
        },
        {
            "location": "黑龙江",
            "data": [
                "7.90",
                "8.44",
                "9.57",
                "7.38"
            ]
        },
        {
            "location": "吉林",
            "data": [
                "7.84",
                "8.46",
                "9.21",
                "7.46"
            ]
        },
        {
            "location": "云南",
            "data": [
                "8.02",
                "8.61",
                "9.29",
                "7.61"
            ]
        },
        {
            "location": "湖北",
            "data": [
                "7.89",
                "8.44",
                "9.60",
                "7.53"
            ]
        },
        {
            "location": "浙江",
            "data": [
                "7.85",
                "8.35",
                "9.14",
                "7.52"
            ]
        },
        {
            "location": "湖南",
            "data": [
                "7.82",
                "8.32",
                "9.12",
                "7.61"
            ]
        }
    ],
    "message": "油价12月19日24时(下周二晚)调整，目前预计下调420元/吨(0.32元/升-0.38元/升)，大家相互转告油价要大跌",
    "news": {
        "text": "油价调整最新消息：今日(12月14日)预计油价下调420元/吨",
        "date": "2023年12月14日"
    },
    "nextTime": ""
}