{
    "today": "2025-03-17 09:26:21.736649",
    "title": [
        "98号汽油",
        "92号汽油",
        "95号汽油",
        "0号柴油"
    ],
    "group": [
        {
            "location": "青海省",
            "data": [
                "8.73",
                "7.48",
                "8.02",
                "7.11"
            ],
            "date": "2025-03-06"
        },
        {
            "location": "西藏",
            "data": [
                "9.91",
                "8.4",
                "8.89",
                "7.72"
            ],
            "date": "2025-03-06"
        },
        {
            "location": "广西",
            "data": [
                "9.4",
                "7.58",
                "8.19",
                "7.24"
            ],
            "date": "2025-03-06"
        },
        {
            "location": "新疆",
            "data": [
                "8.75",
                "7.32",
                "7.83",
                "6.96"
            ],
            "date": "2025-03-06"
        },
        {
            "location": "宁夏",
            "data": [
                "8.96",
                "7.43",
                "7.85",
                "7.07"
            ],
            "date": "2025-03-06"
        },
        {
            "location": "内蒙古",
            "data": [
                "8.74",
                "7.46",
                "7.96",
                "7.06"
            ],
            "date": "2025-03-06"
        },
        {
            "location": "甘肃省",
            "data": [
                "8.6",
                "7.52",
                "8.03",
                "7.09"
            ],
            "date": "2025-03-06"
        },
        {
            "location": "陕西省",
            "data": [
                "10.28",
                "7.41",
                "7.83",
                "7.08"
            ],
            "date": "2025-03-06"
        },
        {
            "location": "云南省",
            "data": [
                "8.91",
                "7.67",
                "8.23",
                "7.25"
            ],
            "date": "2025-03-06"
        },
        {
            "location": "贵州省",
            "data": [
                "8.99",
                "7.65",
                "8.09",
                "7.29"
            ],
            "date": "2025-03-06"
        },
        {
            "location": "四川省",
            "data": [
                "8.85",
                "7.62",
                "8.14",
                "7.23"
            ],
            "date": "2025-03-06"
        },
        {
            "location": "海南省",
            "data": [
                "10.38",
                "8.64",
                "9.17",
                "7.27"
            ],
            "date": "2025-03-06"
        },
        {
            "location": "广东省",
            "data": [
                "10.17",
                "7.54",
                "8.17",
                "7.19"
            ],
            "date": "2025-03-06"
        },
        {
            "location": "湖南省",
            "data": [
                "8.95",
                "7.47",
                "7.95",
                "7.25"
            ],
            "date": "2025-03-06"
        },
        {
            "location": "湖北省",
            "data": [
                "9.68",
                "7.53",
                "8.06",
                "7.17"
            ],
            "date": "2025-03-06"
        },
        {
            "location": "河南省",
            "data": [
                "8.99",
                "7.53",
                "8.04",
                "7.17"
            ],
            "date": "2025-03-06"
        },
        {
            "location": "山东省",
            "data": [
                "8.75",
                "7.49",
                "8.03",
                "7.1"
            ],
            "date": "2025-03-06"
        },
        {
            "location": "江西省",
            "data": [
                "9.53",
                "7.48",
                "8.03",
                "7.23"
            ],
            "date": "2025-03-06"
        },
        {
            "location": "福建省",
            "data": [
                "9.5",
                "7.49",
                "8",
                "7.17"
            ],
            "date": "2025-03-06"
        },
        {
            "location": "安徽省",
            "data": [
                "9.31",
                "7.48",
                "8.01",
                "7.22"
            ],
            "date": "2025-03-06"
        },
        {
            "location": "浙江省",
            "data": [
                "9.17",
                "7.49",
                "7.97",
                "7.16"
            ],
            "date": "2025-03-06"
        },
        {
            "location": "江苏省",
            "data": [
                "9.95",
                "7.49",
                "7.97",
                "7.14"
            ],
            "date": "2025-03-06"
        },
        {
            "location": "黑龙江省",
            "data": [
                "9.14",
                "7.55",
                "8.06",
                "7.03"
            ],
            "date": "2025-03-06"
        },
        {
            "location": "吉林省",
            "data": [
                "8.8",
                "7.49",
                "8.08",
                "7.1"
            ],
            "date": "2025-03-06"
        },
        {
            "location": "辽宁省",
            "data": [
                "8.88",
                "7.66",
                "8.15",
                "7.08"
            ],
            "date": "2025-03-06"
        },
        {
            "location": "山西省",
            "data": [
                "9.62",
                "7.47",
                "8.07",
                "7.25"
            ],
            "date": "2025-03-06"
        },
        {
            "location": "河北省",
            "data": [
                "8.76",
                "7.52",
                "7.94",
                "7.18"
            ],
            "date": "2025-03-06"
        },
        {
            "location": "重庆市",
            "data": [
                "9.69",
                "7.59",
                "8.02",
                "7.25"
            ],
            "date": "2025-03-06"
        },
        {
            "location": "上海市",
            "data": [
                "9.47",
                "7.49",
                "7.97",
                "7.16"
            ],
            "date": "2025-03-06"
        },
        {
            "location": "天津市",
            "data": [
                "9.44",
                "7.52",
                "7.94",
                "7.18"
            ],
            "date": "2025-03-06"
        },
        {
            "location": "北京市",
            "data": [
                "9.51",
                "7.52",
                "8.01",
                "7.23"
            ],
            "date": "2025-03-06"
        }
    ],
    "message": "下次油价3月19日24时调整，目前预计下调油价310元/吨(0.24元/升-0.28元/升)，大家相互转告油价又大跌了",
    "news": {},
    "nextTime": "3月19日"
}